{"last_time": 1749300871.887479, "lat": 51.2601775, "lon": -113.9297323, "rel_alt": 0.092, "alt": 1112.03, "roll": -0.0513705238699913, "pitch": -0.04925644397735596, "yaw": 1.591968297958374, "dlat": 0.35, "dlon": -0.08, "dalt": -0.13, "heading": 91.21, "groundspeed": 0.36322635412216187, "throttle": 0.0, "climb": 0.13048607110977173, "num_satellites": 30.0, "position_uncertainty": 296.0, "alt_uncertainty": 426.0, "flight_mode": 0.0, "battery_voltage": 24697.0, "battery_current": 0.0, "battery_remaining": 99.0}