{"last_time": 1749301124.678785, "lat": 51.259687799999995, "lon": -113.9265487, "rel_alt": 14.732, "alt": 1127.04, "roll": 0.28409409523010254, "pitch": 0.1395990401506424, "yaw": 2.5461854934692383, "dlat": -19.66, "dlon": 5.37, "dalt": -2.46, "heading": 145.88, "groundspeed": 20.384450912475586, "throttle": 74.0, "climb": 2.467146873474121, "num_satellites": 30.0, "position_uncertainty": 331.0, "alt_uncertainty": 518.0, "flight_mode": 5.0, "battery_voltage": 23653.0, "battery_current": 4334.0, "battery_remaining": 95.0}