{"last_time": 1749318033.6015458, "lat": 51.2598858, "lon": -113.92842239999999, "rel_alt": -0.04, "alt": 1112.57, "roll": -0.052740924060344696, "pitch": 0.13915792107582092, "yaw": -2.561293363571167, "dlat": 0.0, "dlon": -0.01, "dalt": 0.01, "heading": 213.25, "groundspeed": 0.017302988097071648, "throttle": 0.0, "climb": -0.018002742901444435, "num_satellites": 30.0, "position_uncertainty": 668.0, "alt_uncertainty": 1152.0, "flight_mode": 0.0, "battery_voltage": 24008.0, "battery_current": 1.0, "battery_remaining": 99.0}