{"last_time": 1749318032.0529857, "lat": 51.2598857, "lon": -113.928422, "rel_alt": -0.27, "alt": 1112.25, "roll": -0.05209037661552429, "pitch": 0.13930419087409973, "yaw": -2.561739444732666, "dlat": 0.0, "dlon": 0.0, "dalt": 0.01, "heading": 213.23, "groundspeed": 0.008933133445680141, "throttle": 0.0, "climb": -0.017644377425312996, "num_satellites": 30.0, "position_uncertainty": 666.0, "alt_uncertainty": 1149.0, "flight_mode": 0.0, "battery_voltage": 23938.0, "battery_current": 0.0, "battery_remaining": 99.0}