{"last_time": 1749289034.7480145, "lat": 51.263269, "lon": -113.93092089999999, "rel_alt": 97.946, "alt": 1212.09, "roll": 0.8908315300941467, "pitch": 0.12274432182312012, "yaw": 0.3687094449996948, "dlat": 32.83, "dlon": 10.17, "dalt": -1.35, "heading": 21.12, "groundspeed": 34.36943054199219, "throttle": 76.0, "climb": 1.3543652296066284, "num_satellites": 25.0, "position_uncertainty": 532.0, "alt_uncertainty": 808.0, "flight_mode": 10.0, "battery_voltage": 22540.0, "battery_current": 4738.0, "battery_remaining": 55.0}