{"last_time": 1749319322.9447634, "lat": 51.2621955, "lon": -113.9302968, "rel_alt": 99.701, "alt": 1214.78, "roll": -0.06041345372796059, "pitch": 0.03802313655614853, "yaw": -0.46928101778030396, "dlat": 21.74, "dlon": -17.98, "dalt": -0.36, "heading": 333.12, "groundspeed": 28.218713760375977, "throttle": 93.0, "climb": 0.3645026385784149, "num_satellites": 30.0, "position_uncertainty": 425.0, "alt_uncertainty": 673.0, "flight_mode": 10.0, "battery_voltage": 22325.0, "battery_current": 7353.0, "battery_remaining": 90.0}