{"last_time": 1749289048.038585, "lat": 51.262873, "lon": -113.9280282, "rel_alt": 96.592, "alt": 1210.74, "roll": -0.007491067051887512, "pitch": -0.006050810217857361, "yaw": 2.672260284423828, "dlat": -12.77, "dlon": 11.01, "dalt": 0.68, "heading": 153.1, "groundspeed": 16.871265411376953, "throttle": 86.0, "climb": -0.682097852230072, "num_satellites": 26.0, "position_uncertainty": 452.0, "alt_uncertainty": 666.0, "flight_mode": 10.0, "battery_voltage": 22233.0, "battery_current": 7330.0, "battery_remaining": 53.0}