{"last_time": 1749319348.3253577, "lat": 51.2615689, "lon": -113.9269817, "rel_alt": 100.414, "alt": 1215.49, "roll": -0.012653615325689316, "pitch": -0.018837913870811462, "yaw": 2.5078296661376953, "dlat": -14.86, "dlon": 8.18, "dalt": -0.06, "heading": 143.68, "groundspeed": 16.972612380981445, "throttle": 75.0, "climb": 0.06271547824144363, "num_satellites": 29.0, "position_uncertainty": 456.0, "alt_uncertainty": 699.0, "flight_mode": 10.0, "battery_voltage": 22772.0, "battery_current": 4463.0, "battery_remaining": 88.0}