{"last_time": 1749321490.888263, "lat": 51.259792499999996, "lon": -113.9286724, "rel_alt": -0.185, "alt": 1113.87, "roll": -0.049353599548339844, "pitch": 0.1461913287639618, "yaw": 2.490114450454712, "dlat": 0.03, "dlon": -0.01, "dalt": 0.0, "heading": 142.67, "groundspeed": 0.0406663715839386, "throttle": 3.0, "climb": -0.005675356835126877, "num_satellites": 26.0, "position_uncertainty": 443.0, "alt_uncertainty": 585.0, "flight_mode": 0.0, "battery_voltage": 24983.0, "battery_current": 0.0, "battery_remaining": 99.0}