{"last_time": 1749289141.812061, "lat": 51.2600069, "lon": -113.9256309, "rel_alt": 99.586, "alt": 1213.73, "roll": -0.014667917042970657, "pitch": 0.03243935853242874, "yaw": 3.0183286666870117, "dlat": -14.56, "dlon": 2.38, "dalt": -0.51, "heading": 172.93, "groundspeed": 14.763760566711426, "throttle": 86.0, "climb": 0.5105655193328857, "num_satellites": 26.0, "position_uncertainty": 431.0, "alt_uncertainty": 678.0, "flight_mode": 10.0, "battery_voltage": 22065.0, "battery_current": 7427.0, "battery_remaining": 39.0}