{"last_time": 1749289161.8115463, "lat": 51.257987, "lon": -113.9266121, "rel_alt": 101.13, "alt": 1215.28, "roll": 0.8161856532096863, "pitch": 0.09624853730201721, "yaw": -1.2804710865020752, "dlat": 18.65, "dlon": -24.28, "dalt": -1.0, "heading": 286.64, "groundspeed": 30.621185302734375, "throttle": 69.0, "climb": 1.0079128742218018, "num_satellites": 24.0, "position_uncertainty": 542.0, "alt_uncertainty": 766.0, "flight_mode": 10.0, "battery_voltage": 22393.0, "battery_current": 4174.0, "battery_remaining": 37.0}