{"last_time": 1749301332.8573008, "lat": 51.2629653, "lon": -113.92890639999999, "rel_alt": 36.233, "alt": 1148.54, "roll": 0.3516307473182678, "pitch": -0.12677888572216034, "yaw": 2.097905397415161, "dlat": -18.66, "dlon": 12.62, "dalt": 3.48, "heading": 120.2, "groundspeed": 22.53493881225586, "throttle": 64.0, "climb": -3.488635301589966, "num_satellites": 28.0, "position_uncertainty": 378.0, "alt_uncertainty": 548.0, "flight_mode": 0.0, "battery_voltage": 23118.0, "battery_current": 2501.0, "battery_remaining": 75.0}