{"last_time": 1749289175.2604315, "lat": 51.2617932, "lon": -113.9282703, "rel_alt": 82.96, "alt": 1197.11, "roll": -0.12948063015937805, "pitch": 0.2654823660850525, "yaw": -0.029091916978359222, "dlat": 31.02, "dlon": -2.84, "dalt": -4.33, "heading": 358.34, "groundspeed": 31.16030502319336, "throttle": 66.0, "climb": 4.336596965789795, "num_satellites": 27.0, "position_uncertainty": 477.0, "alt_uncertainty": 738.0, "flight_mode": 0.0, "battery_voltage": 22540.0, "battery_current": 3721.0, "battery_remaining": 36.0}