{"last_time": 1749321649.700493, "lat": 51.261618, "lon": -113.92658229999999, "rel_alt": 87.938, "alt": 1201.99, "roll": 0.004298783838748932, "pitch": -0.05610279738903046, "yaw": -0.531358003616333, "dlat": 21.03, "dlon": -17.82, "dalt": 1.6, "heading": 329.56, "groundspeed": 27.569562911987305, "throttle": 53.0, "climb": -1.6001884937286377, "num_satellites": 26.0, "position_uncertainty": 455.0, "alt_uncertainty": 572.0, "flight_mode": 10.0, "battery_voltage": 24009.0, "battery_current": 1491.0, "battery_remaining": 84.0}