{"last_time": 1749301413.728234, "lat": 51.258352699999996, "lon": -113.9250797, "rel_alt": 34.752, "alt": 1147.06, "roll": 0.3998367488384247, "pitch": 0.01145327091217041, "yaw": -2.650507926940918, "dlat": -23.72, "dlon": -16.29, "dalt": -0.26, "heading": 208.14, "groundspeed": 28.77829360961914, "throttle": 70.0, "climb": 0.2662316560745239, "num_satellites": 29.0, "position_uncertainty": 350.0, "alt_uncertainty": 538.0, "flight_mode": 5.0, "battery_voltage": 22787.0, "battery_current": 3322.0, "battery_remaining": 68.0}