{"last_time": 1749305080.15618, "lat": 51.258848099999994, "lon": -113.9254014, "rel_alt": 47.429, "alt": 1160.88, "roll": 0.06112981587648392, "pitch": 0.312004029750824, "yaw": 2.3456761837005615, "dlat": -16.67, "dlon": 4.21, "dalt": -3.88, "heading": 134.39, "groundspeed": 17.1993465423584, "throttle": 72.0, "climb": 3.8884389400482178, "num_satellites": 28.0, "position_uncertainty": 320.0, "alt_uncertainty": 527.0, "flight_mode": 0.0, "battery_voltage": 23726.0, "battery_current": 4026.0, "battery_remaining": 94.0}