{"last_time": 1749321740.654918, "lat": 51.2606517, "lon": -113.92624389999999, "rel_alt": 88.317, "alt": 1202.37, "roll": -0.06690262258052826, "pitch": -0.10397252440452576, "yaw": 2.2229483127593994, "dlat": -10.39, "dlon": 12.93, "dalt": 2.56, "heading": 127.36, "groundspeed": 16.59851837158203, "throttle": 56.0, "climb": -2.5677685737609863, "num_satellites": 26.0, "position_uncertainty": 569.0, "alt_uncertainty": 661.0, "flight_mode": 10.0, "battery_voltage": 23844.0, "battery_current": 1826.0, "battery_remaining": 77.0}