{"last_time": 1749305110.4759307, "lat": 51.2598012, "lon": -113.9274585, "rel_alt": 83.039, "alt": 1196.49, "roll": 0.25904977321624756, "pitch": 0.13606873154640198, "yaw": -0.2867375910282135, "dlat": 12.61, "dlon": -13.1, "dalt": -2.55, "heading": 343.58, "groundspeed": 18.19146728515625, "throttle": 100.0, "climb": 2.5528171062469482, "num_satellites": 28.0, "position_uncertainty": 321.0, "alt_uncertainty": 523.0, "flight_mode": 10.0, "battery_voltage": 22785.0, "battery_current": 8429.0, "battery_remaining": 91.0}