{"last_time": 1749321751.0649624, "lat": 51.2596449, "lon": -113.9243236, "rel_alt": 55.926, "alt": 1169.98, "roll": -0.06755422800779343, "pitch": -0.14669962227344513, "yaw": 2.204838752746582, "dlat": -10.2, "dlon": 13.48, "dalt": 3.58, "heading": 126.32, "groundspeed": 16.912046432495117, "throttle": 31.0, "climb": -3.5891759395599365, "num_satellites": 26.0, "position_uncertainty": 497.0, "alt_uncertainty": 577.0, "flight_mode": 10.0, "battery_voltage": 24131.0, "battery_current": 266.0, "battery_remaining": 76.0}