{"last_time": 1749305124.9712496, "lat": 51.2617349, "lon": -113.9296703, "rel_alt": 98.216, "alt": 1211.67, "roll": -0.04744004085659981, "pitch": 0.02281104028224945, "yaw": -0.17409847676753998, "dlat": 14.74, "dlon": -13.57, "dalt": -1.19, "heading": 350.03, "groundspeed": 20.040178298950195, "throttle": 92.0, "climb": 1.1917239427566528, "num_satellites": 28.0, "position_uncertainty": 313.0, "alt_uncertainty": 518.0, "flight_mode": 10.0, "battery_voltage": 23165.0, "battery_current": 5718.0, "battery_remaining": 89.0}