{"last_time": 1749305125.701098, "lat": 51.2618357, "lon": -113.92981759999999, "rel_alt": 98.778, "alt": 1212.23, "roll": -0.03194909915328026, "pitch": 0.040802985429763794, "yaw": -0.147530198097229, "dlat": 14.59, "dlon": -13.52, "dalt": -0.9, "heading": 351.55, "groundspeed": 19.89853286743164, "throttle": 73.0, "climb": 0.9065089225769043, "num_satellites": 28.0, "position_uncertainty": 312.0, "alt_uncertainty": 515.0, "flight_mode": 10.0, "battery_voltage": 23583.0, "battery_current": 3059.0, "battery_remaining": 88.0}