{"last_time": 1749305135.96977, "lat": 51.2630504, "lon": -113.93090509999999, "rel_alt": 98.385, "alt": 1211.84, "roll": 0.4961646497249603, "pitch": 0.04398418217897415, "yaw": 1.010055661201477, "dlat": 4.53, "dlon": 11.59, "dalt": -0.95, "heading": 57.87, "groundspeed": 12.44811725616455, "throttle": 90.0, "climb": 0.9588642716407776, "num_satellites": 27.0, "position_uncertainty": 348.0, "alt_uncertainty": 526.0, "flight_mode": 10.0, "battery_voltage": 22694.0, "battery_current": 8309.0, "battery_remaining": 87.0}