{"last_time": 1749323283.042809, "lat": 51.2627406, "lon": -113.9312099, "rel_alt": 98.917, "alt": 1213.22, "roll": 0.8807578086853027, "pitch": 0.12898273766040802, "yaw": 0.047087009996175766, "dlat": 26.84, "dlon": -5.82, "dalt": -0.16, "heading": 2.69, "groundspeed": 27.471956253051758, "throttle": 94.0, "climb": 0.16931530833244324, "num_satellites": 27.0, "position_uncertainty": 556.0, "alt_uncertainty": 627.0, "flight_mode": 10.0, "battery_voltage": 22530.0, "battery_current": 7646.0, "battery_remaining": 59.0}