{"last_time": 1749305148.4509058, "lat": 51.2623414, "lon": -113.9284521, "rel_alt": 97.725, "alt": 1211.18, "roll": 0.319606214761734, "pitch": 0.015164382755756378, "yaw": 1.390957236289978, "dlat": -3.94, "dlon": 14.58, "dalt": -0.08, "heading": 79.69, "groundspeed": 15.10416030883789, "throttle": 89.0, "climb": 0.08955049514770508, "num_satellites": 28.0, "position_uncertainty": 306.0, "alt_uncertainty": 478.0, "flight_mode": 10.0, "battery_voltage": 22971.0, "battery_current": 6834.0, "battery_remaining": 86.0}