{"last_time": 1749305159.1584628, "lat": 51.261038, "lon": -113.9266497, "rel_alt": 99.539, "alt": 1213.0, "roll": -0.06532488763332367, "pitch": 0.008062750101089478, "yaw": 1.9143587350845337, "dlat": -14.04, "dlon": 11.73, "dalt": -0.46, "heading": 109.68, "groundspeed": 18.301496505737305, "throttle": 79.0, "climb": 0.46113863587379456, "num_satellites": 28.0, "position_uncertainty": 312.0, "alt_uncertainty": 500.0, "flight_mode": 10.0, "battery_voltage": 23029.0, "battery_current": 6398.0, "battery_remaining": 85.0}