{"last_time": 1749305162.0532672, "lat": 51.2607037, "lon": -113.92619579999999, "rel_alt": 98.866, "alt": 1212.32, "roll": -0.06167421489953995, "pitch": -0.0239335298538208, "yaw": 1.8825697898864746, "dlat": -13.13, "dlon": 11.57, "dalt": 0.79, "heading": 107.86, "groundspeed": 17.51021385192871, "throttle": 66.0, "climb": -0.7965682148933411, "num_satellites": 28.0, "position_uncertainty": 313.0, "alt_uncertainty": 500.0, "flight_mode": 10.0, "battery_voltage": 23586.0, "battery_current": 3100.0, "battery_remaining": 85.0}