{"last_time": 1749305540.1274152, "lat": 51.2615779, "lon": -113.9318323, "rel_alt": 25.804, "alt": 1139.26, "roll": -0.4584977328777313, "pitch": 0.02408798784017563, "yaw": -3.0110840797424316, "dlat": -24.74, "dlon": -7.28, "dalt": 0.03, "heading": 187.48, "groundspeed": 25.792211532592773, "throttle": 75.0, "climb": -0.031017083674669266, "num_satellites": 27.0, "position_uncertainty": 289.0, "alt_uncertainty": 481.0, "flight_mode": 8.0, "battery_voltage": 22567.0, "battery_current": 4113.0, "battery_remaining": 53.0}