{"last_time": 1749323374.774648, "lat": 51.2636903, "lon": -113.9288335, "rel_alt": 97.889, "alt": 1212.19, "roll": 0.7517690658569336, "pitch": 0.10558241605758667, "yaw": 1.070678472518921, "dlat": 13.71, "dlon": 11.37, "dalt": -0.79, "heading": 61.34, "groundspeed": 17.818767547607422, "throttle": 85.0, "climb": 0.7921549081802368, "num_satellites": 26.0, "position_uncertainty": 528.0, "alt_uncertainty": 588.0, "flight_mode": 10.0, "battery_voltage": 22549.0, "battery_current": 5976.0, "battery_remaining": 51.0}